AUTHORS
LICENSE
MANIFEST.in
README.rst
setup.cfg
setup.py
django_flatcontent.egg-info/PKG-INFO
django_flatcontent.egg-info/SOURCES.txt
django_flatcontent.egg-info/dependency_links.txt
django_flatcontent.egg-info/not-zip-safe
django_flatcontent.egg-info/requires.txt
django_flatcontent.egg-info/top_level.txt
flatcontent/__init__.py
flatcontent/admin.py
flatcontent/models.py
flatcontent/migrations/0001_initial.py
flatcontent/migrations/0002_auto_20151119_1358.py
flatcontent/migrations/__init__.py
flatcontent/templatetags/__init__.py
flatcontent/templatetags/flatcontent_tags.py
flatcontent/tests/__init__.py
flatcontent/tests/basefactory.py
flatcontent/tests/test_admin.py
flatcontent/tests/test_flatcontent.py
requirements/base.txt
requirements/dev.txt
requirements/test.txt
testproject/__init__.py
testproject/settings.py
testproject/urls.py
testproject/views.py