Metadata-Version: 1.1
Name: django-flatcontent
Version: 0.2.0
Summary: Django FlatContent is intended as a flatpages-like app but for smaller chunks of content that can be edited in the Django admin.
Home-page: http://github.com/orcasgit/django-flatcontent
Author: Oregon Center for Applied Science
Author-email: support@orcasinc.com
License: BSD
Download-URL: http://github.com/orcasgit/django-flatcontent/downloads
Platform: UNKNOWN
Classifier: Development Status :: 4 - Beta
Classifier: Environment :: Web Environment
Classifier: Framework :: Django
Classifier: Intended Audience :: Developers
Classifier: License :: OSI Approved :: BSD License
Classifier: Operating System :: OS Independent
Classifier: Programming Language :: Python
Classifier: Topic :: Software Development :: Libraries :: Python Modules
